Metadata-Version: 2.1
Name: devyl.net
Version: 0.0.0
Summary: Devyl Python SDK (Under developement)
Home-page: https://github.com/devylstudio/python-sdk
Author: Filippo Romani
Author-email: mail@filipporomani.it
Classifier: Programming Language :: Python :: 3
Classifier: Programming Language :: Python :: 3.11
Classifier: Topic :: Software Development :: Libraries :: Python Modules
Classifier: License :: OSI Approved :: MIT License
Classifier: Operating System :: OS Independent
Requires-Python: >=3
License-File: license
